sympytensor/__init__.py
sympytensor/_version.py
sympytensor/pymc.py
sympytensor/pytensor.py
sympytensor-1.3.3.dist-info/METADATA
sympytensor-1.3.3.dist-info/WHEEL
sympytensor-1.3.3.dist-info/licenses/LICENSE
sympytensor-1.3.3.dist-info/RECORD
