Metadata-Version: 2.4
Name: sympytensor
Version: 1.3.3
Summary: Print sympy expressions to pytensor graphs
License: MIT License
License-File: LICENSE
Keywords: computer algebra,pytensor,sympy
Classifier: Development Status :: 4 - Beta
Classifier: Intended Audience :: Science/Research
Classifier: License :: OSI Approved :: MIT License
Classifier: Programming Language :: Python :: 3.10
Classifier: Programming Language :: Python :: 3.11
Classifier: Programming Language :: Python :: 3.12
Classifier: Topic :: Scientific/Engineering
Classifier: Topic :: Scientific/Engineering :: Mathematics
Requires-Python: >=3.10
Requires-Dist: pymc
Requires-Dist: pytensor
Requires-Dist: sympy
Provides-Extra: dev
Requires-Dist: pre-commit; extra == 'dev'
Requires-Dist: pytest; extra == 'dev'
Requires-Dist: pytest-cov; extra == 'dev'
